{"songs": [{"title": "Win My Love", "album": null, "year": "2018-10-17", "lyrics": "[Verse]\nWhy would you wanna bring somethin' between us?\nThere's nothin' between us\nThere's nothin'\nYou're the reason\nYou're the reason that I choose to be distant\nNo one's gonna know that you miss him\nIt's too late, I don't feel love\nAnd to move\nAnd the reason you do\nEven though the baby is mine\nYou will never win my love, no\nYou will never win my love, no, no\nEven if the baby is mine\nYou will never win my love, no\nYou will never win my love, no\nEven if she needs my love, you'll never be sure, no\nOh no, not in love, not in love, no\nYou would seem real lonely\nNo reason, oh\nNo reason, no\nEven if the baby is mine\nYou will never win my love, no\nYou will never get my love, no, no\nEverything you worked on for love\nYou will never get my love, no\nYou will never get my love, no, no, no, no, baby", "image": "https://images.genius.com/3cd68c66d12d757c908ddbdcefb581e8.441x441x1.jpg"}], "artist": "The Weeknd"}